Topsis_Taranpreet_102017050/Topsis.py
Topsis_Taranpreet_102017050/__init__.py
Topsis_Taranpreet_102017050-0.4.dist-info/LICENSE.txt
Topsis_Taranpreet_102017050-0.4.dist-info/METADATA
Topsis_Taranpreet_102017050-0.4.dist-info/WHEEL
Topsis_Taranpreet_102017050-0.4.dist-info/top_level.txt
Topsis_Taranpreet_102017050-0.4.dist-info/RECORD
